{
  "name": [
    "月亮雨自助火锅大骨头",
    "韩盛自助烤肉",
    "优为客牛排自助",
    "鼎香缘海鲜自助火锅",
    "绿波休闲洗浴",
    "和谐号炭火烤肉火锅自助",
    "佳和温泉水世界",
    "鼎香缘海鲜自助火锅烤肉",
    "小猪小牛章鱼水煎肉",
    "爪e玩偶店",
    "好利来",
    "灵芝妹子生蚝米线",
    "小木屋米酒店",
    "丽水云天松骨水会",
    "红龙虾海鲜火锅烤肉自助",
    "碧水流香新桑拿",
    "汤本汤",
    "挪亚海味酒家",
    "华莱士",
    "香悦四季和谐号海鲜烤肉火锅自助",
    "金华大酒店自助餐",
    "零重力蹦床空间",
    "金梦水缘洗浴松骨休闲会馆",
    "歪嘴香重庆鸡公煲",
    "泉溪温泉生活馆",
    "雨竹韩式松骨会所",
    "天河休闲洗浴",
    "阳光洗浴休闲会馆",
    "芙蓉水尚温泉酒店",
    "微客主题量贩KTV"
  ],
  "img": [
    "https://p0.meituan.net/200.0/deal/32618c0a8d4dd4e14ad215f8e2b4aa1d10394.jpg@0_76_370_370a%7C267h_267w_2e_90Q",
    "https://p1.meituan.net/200.0/deal/ef3894e8a1ec3e31e1b56f696036afea21960.jpg",
    "https://p0.meituan.net/200.0/deal/ea2059b1d5d17437d5bdadc325b146b2158180.jpg@280_0_720_720a%7C267h_267w_2e_90Q",
    "https://p0.meituan.net/200.0/deal/d8a4572d3efe292e9773744a591d3041438997.jpg@984_0_1680_1680a%7C267h_267w_2e_90Q",
    "https://p0.meituan.net/200.0/dpdeal/0b48440315505aebe57e23522241cf5177246.jpg",
    "https://p0.meituan.net/200.0/deal/a3f43ca2c30339a08b769f5afdf4a3f813284.jpg@90_0_279_279a%7C267h_267w_2e_90Q",
    "https://p1.meituan.net/200.0/dpdeal/17eae9c8325d40be51379d218786bbc7161836.jpg",
    "https://p0.meituan.net/200.0/deal/d8a4572d3efe292e9773744a591d3041438997.jpg@984_0_1680_1680a%7C267h_267w_2e_90Q",
    "https://p0.meituan.net/200.0/deal/8d78fcba65bc77dff911852305382fc833549.jpg@90_0_280_280a%7C267h_267w_2e_90Q",
    "https://p0.meituan.net/200.0/dpdeal/92a218220f18b8ec16b2b27b1cd20ddf87145.jpg",
    "https://p1.meituan.net/200.0/deal/5698a44ef3d6a12ee3e9ffc29921b256263946.jpg@350_0_900_900a%7C267h_267w_2e_90Q",
    "https://p0.meituan.net/200.0/deal/4b8b2b4b1cc181aa8cb267a18ca41a04393369.jpg@267h_267w_2e_90Q",
    "https://p0.meituan.net/200.0/deal/a34d4541aeb02b9d3d5d9e52b0ba72ef69322.jpg@28_0_1024_1024a%7C267h_267w_2e_90Q",
    "https://p1.meituan.net/200.0/dpdeal/f9bf026f93d0d1d9cafc6f6cf1669e4893660.jpg",
    "https://p0.meituan.net/200.0/deal/5409aa06b9b6db03f429b231663122ac49032.jpg@126_0_388_388a%7C267h_267w_2e_100Q",
    "https://p0.meituan.net/200.0/dpdeal/78b2333707d97fd6ac76df9f332e6d23202683.jpg",
    "https://p1.meituan.net/200.0/dpdeal/df01dcee573b12d615920e94f02e682c206229.jpg",
    "https://p0.meituan.net/200.0/deal/4f5749b168dd71bb5319e296467ba4b1354255.jpg@0_119_481_481a%7C267h_267w_2e_90Q",
    "https://p1.meituan.net/200.0/deal/d3bd153492b50a440fa5c40c1d013c2935756.jpg@117_0_468_468a%7C267h_267w_2e_100q",
    "https://p1.meituan.net/200.0/deal/6fcb501caf9cc334933beb38a2d1677e44024.jpg@107_0_426_426a%7C267h_267w_2e_100Q",
    "https://p0.meituan.net/200.0/deal/b9fd6f9075aa73d2199ea90cf07b605a73032.jpg@97_0_606_606a%7C267h_267w_2e_90Q",
    "https://p0.meituan.net/200.0/dpmerchantpic/353726b300fde3d83790d1126712ecd3470186.jpg",
    "https://p0.meituan.net/200.0/dpdeal/b52951796bdf2c5dff60edee1454322649460.jpg",
    "https://p0.meituan.net/200.0/deal/35085f540e4296045fc89d1945fa39da25763.jpg@125_0_549_549a%7C267h_267w_2e_90Q",
    "https://p1.meituan.net/200.0/dpdeal/435f3cdc48cefc7574969258ca981cdb78435.jpg",
    "https://p0.meituan.net/200.0/dpdeal/76c63155df67f4545faf5100e5df388b71633.jpg",
    "https://p0.meituan.net/200.0/dpdeal/d6c85ca67ba8375e2b247958b12dc4ba517978.jpg",
    "https://p1.meituan.net/200.0/dpdeal/df4bd9a18ea7d32fee38fc015a947f1a131038.jpg",
    "https://p0.meituan.net/200.0/dpdeal/9f78755e542dc99a363916013185cf69415497.jpg",
    "https://p1.meituan.net/200.0/dpdeal/1c1e4d93ca90f501f20452a0ca1c4523185269.jpg"
  ],
  "price": [
    "41.6",
    "73",
    "74",
    "33",
    "78",
    "55",
    "78",
    "128",
    "79.9",
    "3",
    "21",
    "88",
    "69",
    "67.9",
    "58.8",
    "15",
    "138",
    "10.5",
    "79",
    "68",
    "99",
    "49",
    "39.9",
    "52",
    "49",
    "49",
    "49",
    "79",
    "49",
    "49"
  ],
  "del": [
    "45元",
    "98元",
    "79元",
    "48元",
    "79元",
    "99元",
    "98元",
    "85元",
    "6元",
    "100元",
    "232元",
    "88元",
    "108元",
    "19元",
    "23元",
    "100元",
    "78元",
    "98元",
    "88元",
    "168元",
    "20元",
    "119元",
    "68元",
    "78元",
    "69元",
    "78元",
    "98元",
    "40.9元",
    "83元",
    "189元"
  ],
  "title": [
    "[山东路沿线]单人自助",
    "[福佳新天地]自助餐晚餐",
    "[春柳]牛排自助全天接待",
    "[春柳]单人洗浴套票",
    "[3店通用]周六周日法定节假/单人平日晚餐自助2选1",
    "[西安路沿线]高端单人自助",
    "[华南广场]店庆特惠双人洗浴门票",
    "[2店通用]单人周末自助/单人平日晚餐自助2选1",
    "[大连等]【人气】蛋挞1份",
    "[罗斯福购物中心]游戏币100个",
    "[万达广场]特价版双人套餐，包间免费",
    "[春柳]单人经典洗浴套餐",
    "[沙河口区]单人门票+项目6选1套餐",
    "[西岗区]儿童特惠门票",
    "[25店通用]肥牛米线1份",
    "[山东路沿线]100元代金券1张，可叠加",
    "[金州]全天自助/单人自助2选1",
    "[金州]单人晚餐自助",
    "[甘井子区]门票+搓澡（单人）",
    "[金石滩]海鲜大咖1份，包间免费",
    "[大连等]华莱士单人餐，包间免费",
    "[西岗区]周末及节假日单人三小时门票",
    "[罗斯福购物中心]单人浴资搓澡套餐",
    "[周水子机场]套票方案（单人）",
    "[沙河口区]单人特惠门票",
    "[沙河口区]单人洗浴套餐",
    "[西安路沿线]单人休闲洗浴套",
    "[南关岭]超值套餐，建议1-2人使用",
    "[马栏子]单人自助餐",
    "[华南广场]欢唱时段2选1"
  ],
  "sale": [
    "已售2767",
    "已售200624",
    "已售16126",
    "已售67557",
    "已售708615",
    "已售64669",
    "已售1486",
    "已售88079",
    "已售52866",
    "已售22349",
    "已售24620",
    "已售27464",
    "已售41398",
    "已售10101",
    "已售355614",
    "已售2831",
    "已售113761",
    "已售19292",
    "已售14377",
    "已售4186",
    "已售346258",
    "已售4092",
    "已售41952",
    "已售32514",
    "已售39118",
    "已售57639",
    "已售100776",
    "已售854",
    "已售18533",
    "已售16093"
  ]
}
